{
  "type": "minecraft:crafting_shapeless",
  "category": "misc",
  "ingredients": [
    {
      "item": "cornexpansion:popcorn"
    },
    {
      "item": "cornexpansion:popcorn"
    },
    {
      "item": "cornexpansion:popcorn"
    },
    {
      "item": "cornexpansion:popcorn"
    },
    {
      "item": "cornexpansion:popcorn"
    },
    {
      "item": "cornexpansion:popcorn"
    },
    {
      "item": "cornexpansion:popcorn"
    },
    {
      "item": "cornexpansion:popcorn"
    },
    {
      "item": "minecraft:bucket"
    }
  ],
  "result": {
    "item": "cornexpansion:popcorn_tin"
  }
}