{
  "parent": "cornexpansion:getcorn",
  "criteria": {
    "cook_kernels_on_campfire": {
      "conditions": {
        "location": [
          {
            "condition": "minecraft:location_check",
            "predicate": {
              "block": {
                "tag": "minecraft:campfires"
              }
            }
          },
          {
            "condition": "minecraft:match_tool",
            "predicate": {
              "items": [
                "farm_and_charm:kernels"
              ]
            }
          }
        ]
      },
      "trigger": "minecraft:item_used_on_block"
    }
  },
  "display": {
    "announce_to_chat": true,
    "background": "minecraft:textures/gui/advancements/backgrounds/adventure.png",
    "description": {
      "translate": "advancements.cornexpansion.cook_kernels_on_campfire.description"
    },
    "frame": "task",
    "hidden": true,
    "icon": {
      "item": "minecraft:campfire"
    },
    "show_toast": true,
    "title": {
      "translate": "advancements.cornexpansion.cook_kernels_on_campfire.title"
    }
  },
  "requirements": [
    [
      "cook_kernels_on_campfire"
    ]
  ],
  "sends_telemetry_event": true
}